currency_converter_erapi/__init__.py
currency_converter_erapi/apps.py
currency_converter_erapi/converter.py
currency_converter_erapi/exceptions.py
currency_converter_erapi/management/__init__.py
currency_converter_erapi/management/commands/__init__.py
currency_converter_erapi/management/commands/convert_currency.py
django_currency_converter_erapi-1.2.0.dist-info/licenses/LICENSE
tests/__init__.py
tests/conftest.py
tests/settings.py
tests/test_converter.py
django_currency_converter_erapi-1.2.0.dist-info/METADATA
django_currency_converter_erapi-1.2.0.dist-info/WHEEL
django_currency_converter_erapi-1.2.0.dist-info/top_level.txt
django_currency_converter_erapi-1.2.0.dist-info/RECORD
