Metadata-Version: 2.4
Name: django-currency-converter-erapi
Version: 1.2.0
Summary: A Django application for currency conversion using real-time exchange rates
Home-page: https://github.com/mislamdev/django-currency-converter-erapi
Author: MD. MAZHARUL ISLAM
Author-email: mislam@m4a.dev
Project-URL: Bug Reports, https://github.com/mislamdev/django-currency-converter-erapi/issues
Project-URL: Source, https://github.com/mislamdev/django-currency-converter-erapi
Project-URL: Documentation, https://github.com/mislamdev/django-currency-converter-erapi#readme
Keywords: django currency converter exchange rates api finance
Classifier: Development Status :: 5 - Production/Stable
Classifier: Environment :: Web Environment
Classifier: Framework :: Django
Classifier: Framework :: Django :: 3.2
Classifier: Framework :: Django :: 4.0
Classifier: Framework :: Django :: 4.1
Classifier: Framework :: Django :: 4.2
Classifier: Framework :: Django :: 5.0
Classifier: Framework :: Django :: 5.1
Classifier: Framework :: Django :: 5.2
Classifier: Intended Audience :: Developers
Classifier: License :: OSI Approved :: MIT License
Classifier: Operating System :: OS Independent
Classifier: Programming Language :: Python
Classifier: Programming Language :: Python :: 3
Classifier: Programming Language :: Python :: 3.8
Classifier: Programming Language :: Python :: 3.9
Classifier: Programming Language :: Python :: 3.10
Classifier: Programming Language :: Python :: 3.11
Classifier: Programming Language :: Python :: 3.12
Classifier: Topic :: Internet :: WWW/HTTP
Classifier: Topic :: Internet :: WWW/HTTP :: Dynamic Content
Classifier: Topic :: Office/Business :: Financial
Classifier: Topic :: Software Development :: Libraries :: Python Modules
Requires-Python: >=3.8
License-File: LICENSE
Requires-Dist: Django<5.3,>=3.2
Requires-Dist: requests<3.0,>=2.25.0
Provides-Extra: dev
Requires-Dist: pytest>=6.0; extra == "dev"
Requires-Dist: pytest-django>=4.0; extra == "dev"
Requires-Dist: coverage>=5.0; extra == "dev"
Requires-Dist: black>=21.0; extra == "dev"
Requires-Dist: flake8>=3.8; extra == "dev"
Requires-Dist: mypy>=0.800; extra == "dev"
Provides-Extra: dotenv
Requires-Dist: python-dotenv>=0.19.0; extra == "dotenv"
Dynamic: author
Dynamic: author-email
Dynamic: classifier
Dynamic: description
Dynamic: description-content-type
Dynamic: home-page
Dynamic: keywords
Dynamic: license-file
Dynamic: project-url
Dynamic: provides-extra
Dynamic: requires-dist
Dynamic: requires-python
Dynamic: summary
